README.md
setup.cfg
setup.py
wagtail_mvc/__init__.py
wagtail_mvc/decorators.py
wagtail_mvc/models.py
wagtail_mvc/views.py
wagtail_mvc.egg-info/PKG-INFO
wagtail_mvc.egg-info/SOURCES.txt
wagtail_mvc.egg-info/dependency_links.txt
wagtail_mvc.egg-info/top_level.txt
wagtail_mvc/tests/__init__.py
wagtail_mvc/tests/test_decorators.py
wagtail_mvc/tests/test_models.py
wagtail_mvc/tests/test_views.py
wagtail_mvc/tests/test_app/__init__.py
wagtail_mvc/tests/test_app/factories.py
wagtail_mvc/tests/test_app/models.py
wagtail_mvc/tests/test_app/urls.py
wagtail_mvc/tests/test_app/views.py
wagtail_mvc/tests/test_app/migrations/0001_initial.py
wagtail_mvc/tests/test_app/migrations/__init__.py