Metadata-Version: 1.1
Name: wagtail-mvc
Version: 0.3.0
Summary: Allows better separation between models and views in Wagtail CMS
Home-page: https://github.com/fatboystring/Wagtail-MVC/
Author: Dan Stringer
Author-email: dan.stringer1983@googlemail.com
License: MIT
Download-URL: https://github.com/fatboystring/Wagtail-MVC/tarball/0.1.0
Keywords: wagtail,django,mvc
Platform: UNKNOWN
Classifier: Development Status :: 4 - Beta
Classifier: Intended Audience :: Developers
Classifier: Topic :: Software Development :: Libraries :: Python Modules
Classifier: License :: OSI Approved :: MIT License
Classifier: Programming Language :: Python :: 2
Classifier: Programming Language :: Python :: 2.7
Classifier: Programming Language :: Python :: 3
Classifier: Programming Language :: Python :: 3.4
Classifier: Programming Language :: Python :: 3.5
